dashai_translation_plugin/__init__.py
dashai_translation_plugin/translation_metric.py
dashai_translation_plugin/translation_model.py
dashai_translation_plugin/translation_task.py
dashai_translation_plugin/metrics/bleu.py
dashai_translation_plugin/metrics/ter.py
dashai_translation_plugin/models/opus_mt_en_es_transformer.py
dashai_translation_plugin-0.0.2.dist-info/METADATA
dashai_translation_plugin-0.0.2.dist-info/WHEEL
dashai_translation_plugin-0.0.2.dist-info/entry_points.txt
dashai_translation_plugin-0.0.2.dist-info/RECORD
