Metadata-Version: 2.3
Name: dashai_translation_plugin
Version: 0.0.2
Summary: Translation Plugin
Author: DashAI team
Author-email: dashaisoftware@gmail.com
Keywords: DashAI,Metric,Model,Task
Requires-Python: >=3.8
Requires-Dist: dashai-test-text-classification-plugin
Requires-Dist: datasets>=2.19.2
Requires-Dist: scikit-learn==1.2.1
Requires-Dist: transformers==4.23.1
